{
  "data": [
    {
      "name": "Projeto Alpha",
      "repository": "REPO1"
    },
    {
      "name": "Projeto Beta",
      "repository": "REPO1"
    },
    {
      "name": "Projeto Gamma",
      "repository": "REPO1"
    },
    {
      "name": "Projeto Delta",
      "repository": "REPO1"
    },
    {
      "name": "Projeto Epsilon",
      "repository": "REPO1"
    },
    {
      "name": "Projeto Zeta",
      "repository": "REPO1"
    },
    {
      "name": "Projeto Eta",
      "repository": "REPO1"
    },
    {
      "name": "Projeto Theta",
      "repository": "REPO1"
    },
    {
      "name": "Projeto Iota",
      "repository": "REPO1"
    },
    {
      "name": "Projeto Kappa",
      "repository": "REPO1"
    }
  ]
}
